doorloop/__init__.py
doorloop/accounts.py
doorloop/base.py
doorloop/communications.py
doorloop/draft_leases.py
doorloop/expenses.py
doorloop/files.py
doorloop/lease_charges.py
doorloop/lease_credits.py
doorloop/lease_payments.py
doorloop/lease_returned_payments.py
doorloop/leases.py
doorloop/main.py
doorloop/notes.py
doorloop/owners.py
doorloop/portfolios.py
doorloop/properties.py
doorloop/reports.py
doorloop/tasks.py
doorloop/tenants.py
doorloop/units.py
doorloop/users.py
doorloop/vendor_bills.py
doorloop/vendor_credits.py
doorloop/vendors.py
doorloop-0.0.6.dist-info/METADATA
doorloop-0.0.6.dist-info/WHEEL
doorloop-0.0.6.dist-info/licenses/LICENSE
doorloop-0.0.6.dist-info/RECORD
